{"type":"PR","pr":{"number":8,"head":"cbddf1e77ec5513d1eb7c200adce264afeedff3a"},"user":"Diego Garcia","status":"draft","branch":"cms/posts/2020-01-11-angular-material - entendendo-como-funciona-sua-tematização-parte-ii","collection":"posts","commitMessage":"Create Posts “2020-01-11-angular-material - entendendo-como-funciona-sua-tematização-parte-ii”","title":"Angular Material   Entendendo como funciona sua tematização (Parte II)","description":"No último post vimos sobre o Material Design e Angular Material.Falamos sobre como o Angular Material trabalha em sua tematização aplicada no framework. Nessa continuação vamos criar nosso próprio componente utilizando a tematização de paletas.","objects":{"entry":{"path":"posts/2020-01-11-angular-material - entendendo-como-funciona-sua-tematização-parte-ii.md","sha":"1e7012c38ef00fb6f442fb59c2c428a60ce82426"},"files":[]},"timeStamp":"2020-01-11T13:53:28.700Z","version":"1"}